vpype_vectrace/iread.py
vpype_vectrace-0.1.2.dist-info/LICENSE
vpype_vectrace-0.1.2.dist-info/METADATA
vpype_vectrace-0.1.2.dist-info/WHEEL
vpype_vectrace-0.1.2.dist-info/entry_points.txt
vpype_vectrace-0.1.2.dist-info/top_level.txt
vpype_vectrace-0.1.2.dist-info/RECORD
