Metadata-Version: 2.1
Name: vpype-vectrace
Version: 0.1.2
Summary: vpype polygon tracer plugin
Home-page: https://github.com/tatarize/vpype-vectrace/
Author: Tatarize
Author-email: tatarize@gmail.com
License: UNKNOWN
Platform: UNKNOWN
Classifier: Programming Language :: Python :: 3.6
Classifier: Programming Language :: Python :: 3.7
Classifier: Programming Language :: Python :: 3.8
Classifier: Programming Language :: Python :: 3.9
Classifier: Programming Language :: Python :: 3.10
Classifier: License :: OSI Approved :: MIT License
Classifier: Operating System :: OS Independent
Requires-Dist: click
Requires-Dist: vpype (<2.0,>=1.10)
Requires-Dist: Pillow
Requires-Dist: svgelements
